wicker/__init__.py
wicker/core/__init__.py
wicker/core/abstract.py
wicker/core/column_files.py
wicker/core/config.py
wicker/core/datasets.py
wicker/core/definitions.py
wicker/core/errors.py
wicker/core/filelock.py
wicker/core/persistance.py
wicker/core/shuffle.py
wicker/core/storage.py
wicker/core/utils.py
wicker/core/writer.py
wicker/plugins/__init__.py
wicker/plugins/dynamodb.py
wicker/plugins/flyte.py
wicker/plugins/spark.py
wicker/plugins/wandb.py
wicker/schema/__init__.py
wicker/schema/codecs.py
wicker/schema/dataloading.py
wicker/schema/dataparsing.py
wicker/schema/schema.py
wicker/schema/serialization.py
wicker/schema/validation.py
wicker/testing/__init__.py
wicker/testing/codecs.py
wicker/testing/storage.py
wicker-0.0.16.dist-info/LICENSE
wicker-0.0.16.dist-info/METADATA
wicker-0.0.16.dist-info/WHEEL
wicker-0.0.16.dist-info/top_level.txt
wicker-0.0.16.dist-info/RECORD
