Metadata-Version: 2.1
Name: wicker
Version: 0.0.16
Summary: An open source framework for Machine Learning dataset storage and serving
Home-page: https://github.com/woven-planet/Wicker
Author: wicker-maintainers
Author-email: wicker-maintainers@woven-planet.global
Project-URL: Bug Tracker, https://github.com/woven-planet/Wicker/issues
Classifier: Programming Language :: Python :: 3
Classifier: License :: OSI Approved :: Apache Software License
Classifier: Operating System :: OS Independent
Requires-Python: >=3.6
License-File: LICENSE
Requires-Dist: numpy
Requires-Dist: pyarrow
Requires-Dist: boto3
Provides-Extra: dynamodb
Requires-Dist: pynamodb; extra == "dynamodb"
Provides-Extra: flyte
Requires-Dist: flytekit; extra == "flyte"
Provides-Extra: spark
Requires-Dist: pyspark; extra == "spark"
Provides-Extra: wandb
Requires-Dist: wandb; extra == "wandb"
